{"cameraMode":{"drawMode":0,"name":"Shaded","section":"Shading Mode"},"sceneLighting":false,"audioPlay":false,"sceneViewState":{"m_AlwaysRefresh":false,"showFog":true,"showSkybox":false,"showFlares":true,"showImageEffects":true,"showParticleSystems":true,"showVisualEffectGraphs":true,"m_FxEnabled":true},"in2DMode":false,"pivot":{"x":5.645915508270264,"y":1.8726420402526856,"z":4.3914995193481449},"rotation":{"x":0.0544574111700058,"y":-0.9106356501579285,"z":0.1283465176820755,"w":0.3902994394302368},"size":0.8054581880569458,"orthographic":false}